genedataset/__init__.py
genedataset/dataset.py
genedataset/geneset.py
genedataset/data/Genes.20171020.h5
genedataset/data/Genes.h5
genedataset/data/ProbeIdGeneIdMapping_Affymetrix.txt
genedataset/data/ProbeIdGeneIdMapping_IlluminaWG6.txt
genedataset/data/hsgenesetExon.txt
genedataset/data/testdata.h5
genedataset-0.6.2.dist-info/METADATA
genedataset-0.6.2.dist-info/RECORD
genedataset-0.6.2.dist-info/WHEEL
genedataset-0.6.2.dist-info/top_level.txt
