Metadata-Version: 2.1
Name: genedataset
Version: 0.6.2
Summary: Store and access gene expression datasets and gene definitions.
Home-page: https://github.com/jarny/genedataset
Author: Jarny Choi
Author-email: jarny.choi@gmail.com
License: UNKNOWN
Keywords: gene microarray rna-seq
Platform: UNKNOWN
Classifier: Programming Language :: Python :: 2.7
Classifier: Topic :: Scientific/Engineering :: Bio-Informatics
Requires-Dist: pandas
